tsad/__init__.py
tsad/pipelines.py
tsad/base/__init__.py
tsad/base/datasets.py
tsad/base/exceptions.py
tsad/base/pipeline.py
tsad/base/task.py
tsad/base/wrappers.py
tsad/tasks/__init__.py
tsad/tasks/deep_learning_anomaly_detection.py
tsad/tasks/deep_learning_forecasting.py
tsad/tasks/eda.py
tsad/tasks/feature_generation.py
tsad/tasks/feature_selection.py
tsad/tasks/preprocess.py
tsad/tasks/visualization.py
tsad/utils/__init__.py
tsad/utils/eda.py
tsad/utils/imports.py
tsad/utils/iterators.py
tsad/utils/preproc.py
tsad/utils/trainTestSplitting.py
tsad/utils/visualization.py
tsad/utils/ResidualAnomalyDetectionUtils/__init__.py
tsad/utils/ResidualAnomalyDetectionUtils/feature_importance.py
tsad/utils/ResidualAnomalyDetectionUtils/generateResidual.py
tsad/utils/ResidualAnomalyDetectionUtils/stastics.py
tsad/utils/evaluating/__init__.py
tsad/utils/evaluating/evaluating.py
tsad/utils/evaluating/src.py
tsad/utils/evaluating/univariate_funcs.py
tsad/utils/featproc/__init__.py
tsad/utils/featproc/toSpike.py
tsad/utils/ml_models/__init__.py
tsad/utils/ml_models/deeplearning_regressors.py
tsad/utils/ml_models/fitUtils.py
tsad/utils/ml_models/nn_for_anomaly_detection.py
tsad-0.19.4.dist-info/LICENSE
tsad-0.19.4.dist-info/METADATA
tsad-0.19.4.dist-info/WHEEL
tsad-0.19.4.dist-info/top_level.txt
tsad-0.19.4.dist-info/RECORD
