Metadata-Version: 2.1
Name: tsad
Version: 0.19.4
Summary: Time Series Analysis for Simulation of Technological Processes
Home-page: https://github.com/waico/tsad
Author: Viacheslav Kozitsin, Oleg Berezin, Iurii Katser, Ivan Maximov
Author-email: rfptk2525@yandex.ru
License: GNU GPLv3
Requires-Python: >=3.10.0
License-File: LICENSE
Requires-Dist: ipykernel ==6.25.1
Requires-Dist: ipython ==8.14.0
Requires-Dist: matplotlib ==3.7.1
Requires-Dist: missingno ==0.5.2
Requires-Dist: numpy ==1.25.0
Requires-Dist: pandas ==1.5.3
Requires-Dist: plotly ==5.16.1
Requires-Dist: plotly-resampler ==0.9.1
Requires-Dist: pyarrow ==14.0.1
Requires-Dist: scikit-learn ==1.1.2
Requires-Dist: statsmodels ==0.14.1
Requires-Dist: tsfel ==0.1.6
Requires-Dist: tsflex ==0.3.0
Requires-Dist: tsfresh ==0.20.1
Requires-Dist: torch ==1.11.0
Requires-Dist: xlrd ==2.0.1
